{
  "body": "Visit a sustainable farm and vineyard which includes an organic blueberry farm. Meet the proprietor and walk with her on some of her 100 acres of ocean view hills above Lompoc. After the tour enjoy sipping the award-winning french inspired wine she has grown on the property. Lunch included. This tour is $110 per person beginning at 11am and ending at 2pm.  If you choose to add a second private vineyard tour and tasting the cost is $160 per person and begins at 11am and ends at 4pm.\n\nPlease call to book this tour.",
  "priceLong": "Starting at $110.00 per person.",
  "timeLong": "11am-2pm\n\nor\n\n11am-4pm",
  "thumbnail": "https://ucarecdn.com/72691b49-ea72-4498-8763-6c1928688509/",
  "gallery": [
    "https://ucarecdn.com/2ea945cf-064c-4a9f-b1ec-04eb5c1dc66e/"
  ],
  "priceShort": "$110.00/160.00 ",
  "title": "Deluxe Private Vineyard Visit",
  "booking": {
    "includesPickup": false,
    "email": {
      "boatlaunchDirections": false,
      "stableDirections": false,
      "gratuity": "Please bring cash to tip your guide."
    }
  },
  "sort": 4
}